blind_rt60/__init__.py
blind_rt60/estimation.py
blind_rt60/utils.py
blind_rt60/version.py
blind_rt60-0.1.1.dist-info/LICENSE
blind_rt60-0.1.1.dist-info/METADATA
blind_rt60-0.1.1.dist-info/WHEEL
blind_rt60-0.1.1.dist-info/top_level.txt
blind_rt60-0.1.1.dist-info/RECORD
