Metadata-Version: 2.1
Name: blind_rt60
Version: 0.1.1
Summary: The BlindRT60 algorithm is used to estimate the reverberation time (RT60) of a room based on the recorded audio signals from microphones
Home-page: https://github.com/nuniz/blind_rt60
Author: Asaf Zorea
Author-email: zoreasaf@gmail.com
License: MIT
Classifier: Programming Language :: Python :: 3
Classifier: License :: OSI Approved :: MIT License
Classifier: Operating System :: OS Independent
Requires-Python: >=3.6
License-File: LICENSE
Requires-Dist: scipy
Requires-Dist: numpy
Requires-Dist: matplotlib
Provides-Extra: dev
Requires-Dist: pyroomacoustics ; extra == 'dev'
Requires-Dist: parameterized ; extra == 'dev'
Requires-Dist: pre-commit ; extra == 'dev'
